LICENSE
MANIFEST.in
README.md
setup.cfg
setup.py
tap_freshdesk/__init__.py
tap_freshdesk/utils.py
tap_freshdesk.egg-info/PKG-INFO
tap_freshdesk.egg-info/SOURCES.txt
tap_freshdesk.egg-info/dependency_links.txt
tap_freshdesk.egg-info/entry_points.txt
tap_freshdesk.egg-info/requires.txt
tap_freshdesk.egg-info/top_level.txt
tap_freshdesk/schemas/agents.json
tap_freshdesk/schemas/companies.json
tap_freshdesk/schemas/contacts.json
tap_freshdesk/schemas/conversations.json
tap_freshdesk/schemas/groups.json
tap_freshdesk/schemas/roles.json
tap_freshdesk/schemas/satisfaction_ratings.json
tap_freshdesk/schemas/tickets.json
tap_freshdesk/schemas/time_entries.json
tests/test_freshdesk_bookmarks.py
tests/test_freshdesk_check.py
tests/test_freshdesk_pagination.py
tests/test_freshdesk_start_date.py