Metadata-Version: 2.1
Name: tap-freshdesk
Version: 0.11.1
Summary: Singer.io tap for extracting data from the Freshdesk API
Home-page: http://singer.io
Author: Stitch
License: UNKNOWN
Platform: UNKNOWN
Classifier: Programming Language :: Python :: 3 :: Only
License-File: LICENSE
